[
{"name": "CERN_PDUNE_EOS_to_RAL_ECHO", "source": "CERN_PDUNE_EOS", "destination": "RAL_ECHO", "reason": "tx_error", "count": 2},
{"name": "CERN_PDUNE_EOS_to_QMUL", "source": "CERN_PDUNE_EOS", "destination": "QMUL", "reason": "tx_error", "count": 1},
{"name": "CERN_PDUNE_CASTOR_to_RAL_ECHO", "source": "CERN_PDUNE_CASTOR", "destination": "RAL_ECHO", "reason": "tx_error", "count": 2},
{"name": "FNAL_DCACHE_to_RAL_ECHO", "source": "FNAL_DCACHE", "destination": "RAL_ECHO", "reason": "tx_error", "count": 2}
]